fastapi_oauth2_mongodb/__init__.py
fastapi_oauth2_mongodb/__main__.py
fastapi_oauth2_mongodb/fastapi_oauth2_mongodb.py
fastapi_oauth2_mongodb-0.0.4.dist-info/METADATA
fastapi_oauth2_mongodb-0.0.4.dist-info/WHEEL
fastapi_oauth2_mongodb-0.0.4.dist-info/entry_points.txt
fastapi_oauth2_mongodb-0.0.4.dist-info/top_level.txt
fastapi_oauth2_mongodb-0.0.4.dist-info/RECORD
